library/__init__.py
library/circle.py
library_test/__init__.py
library_test/circle.py
test_library_juanmferreira93-0.0.1.dist-info/METADATA
test_library_juanmferreira93-0.0.1.dist-info/WHEEL
test_library_juanmferreira93-0.0.1.dist-info/top_level.txt
test_library_juanmferreira93-0.0.1.dist-info/RECORD
