Metadata-Version: 2.1
Name: test_library_juanmferreira93
Version: 0.0.1
Summary: This is a test library
Author: Juanma Ferreira
